LICENSE.txt
README.md
setup.py
cmdwordplay/__init__.py
cmdwordplay.egg-info/PKG-INFO
cmdwordplay.egg-info/SOURCES.txt
cmdwordplay.egg-info/dependency_links.txt
cmdwordplay.egg-info/top_level.txt
tests/__init__.py
tests/test.py