Metadata-Version: 2.1
Name: cmdwordplay
Version: 0.0.2
Summary: Quickly build command-line word games
Home-page: https://github.com/sgj123456/cmdwordplay
Author: maopao
Author-email: 2586743928@qq.com
Classifier: Programming Language :: Python :: 3
Classifier: License :: OSI Approved :: MIT License
Classifier: Operating System :: OS Independent
Requires-Python: >=3.6
License-File: LICENSE.txt
